{
"type": "FeatureCollection",
"crs": { "type": "name", "properties": { "name": "urn:ogc:def:crs:OGC:1.3:CRS84" } },
"features": [
{ "type": "Feature", "properties": { "panoid": "Rq0aGRxXi8wJrI2OMZOtSg", "building-id": 276, "face-index": 7.0, "fov": 171.88918618836647, "distance": 6.2359580488864204, "face-image": "\/media\/femianjc\/My Book\/svextract\/data\/walls\/copenhagen_denmark\/copenhagen_denmark-000276-000007-Rq0aGRxXi8wJrI2OMZOtSg.jpg", "heading": 336.8865966796875, "tilt": 90.19293212890625, "roll": -0.77592986822128296, "year": null, "month": null, "url": "https:\/\/maps.googleapis.com\/maps\/api\/streetview?size=400x400&pano=Rq0aGRxXi8wJrI2OMZOtSg&fov=90&heading=23.1134033203&pitch=0" }, "geometry": { "type": "Point", "coordinates": [ 12.61634390199958, 55.664272655592363 ] } }
]
}
